LICENSE.txt
MANIFEST.in
README.md
setup.py
cryptographys/__init__.py
cryptographys.egg-info/PKG-INFO
cryptographys.egg-info/SOURCES.txt
cryptographys.egg-info/dependency_links.txt
cryptographys.egg-info/top_level.txt