Metadata-Version: 2.1
Name: cryptographys
Version: 0.0.1
Summary: A library focused on encryption and decryption in various ways (like morse, cesar cipher, binary etc)
Home-page: UNKNOWN
Author: Yoda
Author-email: rvln10@gmail.com
License: MIT
Platform: UNKNOWN
Classifier: Development Status :: 5 - Production/Stable
Classifier: Intended Audience :: Education
Classifier: Operating System :: Microsoft :: Windows :: Windows 10
Classifier: License :: OSI Approved :: MIT License
Classifier: Programming Language :: Python :: 3
License-File: LICENSE.txt
